vix_utils/__init__.py
vix_utils/cfe-rule-book.pdf
vix_utils/continuous_maturity.py
vix_utils/data_notes.md
vix_utils/download_vix_futures.py
vix_utils/futures_utils.py
vix_utils/location.py
vix_utils/old_download_vix_futures.py
vix_utils/vix_cash_term_structure.py
vix_utils/vix_futures_dates.py
vix_utils/vixutil.py
vix_utils/examples/a_t.ipynb
vix_utils/examples/hello_x.py
vix_utils/examples/sample_load_data.py
vix_utils/examples/sample_plots.py
vix_utils/examples/vix_utils xarray.ipynb
vix_utils/examples/vix_utils.ipynb
vix_utils-0.1.7.dist-info/entry_points.txt
vix_utils-0.1.7.dist-info/WHEEL
vix_utils-0.1.7.dist-info/METADATA
vix_utils-0.1.7.dist-info/RECORD
