Metadata-Version: 2.1
Name: vix_utils
Version: 0.1.7
Summary: Provide VIX Cash and Futures Term Structure as Pandas dataframes
Keywords: vix,volatility,pandas,vix term structure,cboe
Author-email: Doug Ransom <doug@ransom.vip>
Requires-Python: >=3.10
Classifier: License :: OSI Approved :: MIT License
Classifier: Development Status :: 3 - Alpha
Classifier: Intended Audience :: Financial and Insurance Industry
Classifier: Topic :: Office/Business :: Financial :: Investment
Requires-Dist: pandas
Requires-Dist: pandas-market-calendars >= 4.4.0
Requires-Dist: aiofiles
Requires-Dist: aiohttp[speedups]
Requires-Dist: openpyxl
Requires-Dist: appdirs
Requires-Dist: more_itertools
Requires-Dist: icecream
Requires-Dist: matplotlib ; extra == "examples"
Requires-Dist: scipy ; extra == "examples"
Requires-Dist: pytest ; extra == "test"
Project-URL: home-page, https://github.com/dougransom/vix_utils
Provides-Extra: examples
Provides-Extra: test
